parkinglotgym/__init__.py
parkinglotgym/parking_lot_env.py
parkinglotgym/register_env.py
parkinglotgym-1.1.3.dist-info/licenses/LICENSE
parkinglotgym-1.1.3.dist-info/METADATA
parkinglotgym-1.1.3.dist-info/WHEEL
parkinglotgym-1.1.3.dist-info/top_level.txt
parkinglotgym-1.1.3.dist-info/RECORD
