Metadata-Version: 2.4
Name: parkinglotgym
Version: 1.1.3
Summary: Gym library for training RL agents on Rush Hour game
Author-email: Evaldas Visockas <developersediary@gmail.com>
License: GPL-3.0-or-later
Project-URL: Repository, https://github.com/EvalVis/ParkingLotGym
Requires-Python: >=3.12
License-File: LICENSE
Requires-Dist: gymnasium>=1.1.1
Requires-Dist: numpy>=2.2.3
Requires-Dist: matplotlib>=3.10.1
Requires-Dist: parkinglotpuzzle>=1.0.0
Provides-Extra: dev
Requires-Dist: pytest>=8.3.4; extra == "dev"
Requires-Dist: pytest-cov>=6.1.1; extra == "dev"
Dynamic: license-file
